repository_cli/__init__.py
repository_cli/cli.py
repository_cli/click_options.py
repository_cli/click_param_types.py
repository_cli/config.py
repository_cli/ext.py
repository_cli/generate_commands.py
repository_cli/records.py
repository_cli/types.py
repository_cli/users.py
repository_cli/utils.py
repository_cli-0.12.2.dist-info/AUTHORS.rst
repository_cli-0.12.2.dist-info/LICENSE
repository_cli-0.12.2.dist-info/METADATA
repository_cli-0.12.2.dist-info/WHEEL
repository_cli-0.12.2.dist-info/entry_points.txt
repository_cli-0.12.2.dist-info/top_level.txt
repository_cli-0.12.2.dist-info/RECORD
