Metadata-Version: 2.1
Name: repository-cli
Version: 0.12.2
Summary: "CLI utilities for TU Graz Repository."
Home-page: https://github.com/inveniosoftware/repository-cli
Author: Graz University of Technology
Author-email: info@inveniosoftware.org
License: MIT
Keywords: invenio repository cli
Platform: any
Classifier: Programming Language :: Python :: 3.12
Classifier: Development Status :: 5 - Production/Stable
Requires-Python: >=3.12
License-File: LICENSE
License-File: AUTHORS.rst
Requires-Dist: click >=8.0.0
Requires-Dist: invenio-rdm-records[opensearch2] >=4.0.0
Requires-Dist: invenio-records-marc21 >=0.9
Requires-Dist: invenio-records-lom >=0.10
Requires-Dist: jq >=1.4.0
Requires-Dist: tabulate >=0.9.0
Provides-Extra: tests
Requires-Dist: pytest-invenio >=1.4.0 ; extra == 'tests'
Requires-Dist: pytest-black-ng >=0.4.0 ; extra == 'tests'
Requires-Dist: invenio-app >=1.3.0 ; extra == 'tests'
Requires-Dist: invenio-search[opensearch2] >=2.1.0 ; extra == 'tests'
Requires-Dist: invenio-cache >=1.1.1 ; extra == 'tests'
Requires-Dist: Sphinx >=7.0.0 ; extra == 'tests'
Requires-Dist: sphinx-click >=6.0.0 ; extra == 'tests'
Requires-Dist: ruff >=0.5.3 ; extra == 'tests'
